pyenvar/__init__.py
pyenvar-1.0.6.data/scripts/pyenvar-cli
pyenvar-1.0.6.dist-info/LICENSE.md
pyenvar-1.0.6.dist-info/METADATA
pyenvar-1.0.6.dist-info/WHEEL
pyenvar-1.0.6.dist-info/top_level.txt
pyenvar-1.0.6.dist-info/RECORD
