Metadata-Version: 2.1
Name: pyenvar
Version: 1.0.6
Summary: .env loader for python
Home-page: https://github.com/wuriyanto48/pyenvar
Author: wuriyanto
Author-email: wuriyanto48@yahoo.co.id
License: UNKNOWN
Project-URL: Bug Reports, https://github.com/wuriyanto48/pyenvar/issues
Project-URL: Source, https://github.com/wuriyanto48/pyenvar/
Keywords: env variable,.env,config,dotenv
Platform: UNKNOWN
Classifier: Development Status :: 3 - Alpha
Classifier: Intended Audience :: Developers
Classifier: Environment :: Console
Classifier: License :: OSI Approved :: MIT License
Classifier: Programming Language :: Python :: 3
Classifier: Programming Language :: Python :: 3.5
Classifier: Programming Language :: Python :: 3.6
Classifier: Programming Language :: Python :: 3.7
Classifier: Programming Language :: Python :: 3.8
Classifier: Programming Language :: Python :: 3 :: Only
Requires-Python: >=3.5
